airzonecloud/AirzoneCloudConnector.py
airzonecloud/AirzoneDevice.py
airzonecloud/AirzoneInstallation.py
airzonecloud/AirzoneWebsocket.py
airzonecloud/const.py
tests/__init__.py
tests/test_device.py
tests/test_installation.py
python_airzonecloud-0.0.10.dist-info/LICENSE
python_airzonecloud-0.0.10.dist-info/METADATA
python_airzonecloud-0.0.10.dist-info/WHEEL
python_airzonecloud-0.0.10.dist-info/top_level.txt
python_airzonecloud-0.0.10.dist-info/RECORD
