Metadata-Version: 2.1
Name: python-airzonecloud
Version: 0.0.10
Summary: A package to connect to AirZone cloud
Home-page: https://github.com/jlmaroto/python-airzonecloud
Author: José Luis Maroto
Author-email: maroto.joseluis@gmail.com
License: UNKNOWN
Platform: UNKNOWN
Classifier: Programming Language :: Python :: 3
Classifier: License :: OSI Approved :: MIT License
Classifier: Operating System :: OS Independent
License-File: LICENSE
